AUTHORS.txt
CHANGES.txt
LICENSES.txt
MANIFEST.in
README.txt
runtests.py
setup.cfg
setup.py
quotachecker/__init__.py
quotachecker/cmd_input.py
quotachecker/csv_output.py
quotachecker.egg-info/PKG-INFO
quotachecker.egg-info/SOURCES.txt
quotachecker.egg-info/dependency_links.txt
quotachecker.egg-info/entry_points.txt
quotachecker.egg-info/not-zip-safe
quotachecker.egg-info/top_level.txt
tests/test_cmd_input.py
tests/test_csv_output.py
tests/test_init.py