Metadata-Version: 1.1
Name: quotachecker
Version: 1.7
Summary: Return the quota of 1st level sub folders in a directory.
Home-page: https://bitbucket.org/inqbus/quotachecker
Author: Frank Schneider
Author-email: frank.schneider@inqbus.de
License: BSD
Download-URL: http://pypi.python.org/pypi/quotachecker
Platform: UNKNOWN
Classifier: Development Status :: 4 - Beta
Classifier: Environment :: Console
Classifier: Intended Audience :: System Administrators
Classifier: License :: OSI Approved :: BSD License
Classifier: Natural Language :: English
Classifier: Operating System :: Unix
Classifier: Programming Language :: Python :: 2.6
Classifier: Programming Language :: Python :: 2.7
